yarp/__init__.py
yarp/exceptions/__init__.py
yarp/exceptions/base.py
yarp/exceptions/local_memory_exceptions.py
yarp/exceptions/runtime.py
yarp/models/__init__.py
yarp/models/vector_models.py
yarp/runtime/__init__.py
yarp/runtime/preflight_checks.py
yarp/vector_index/__init__.py
yarp/vector_index/local_vector_index.py
python_yarp-0.3.4.dist-info/METADATA
python_yarp-0.3.4.dist-info/WHEEL
python_yarp-0.3.4.dist-info/licenses/LICENSE
python_yarp-0.3.4.dist-info/RECORD
