Metadata-Version: 2.3
Name: python-yarp
Version: 0.3.4
Summary: Yet Another RAG Pipeline(YARP) with strong focus on In Memory Vector DB with ANN
Project-URL: Homepage, https://github.com/regmibijay/yarp
Project-URL: Documentation, https://regmibijay.github.io/yarp
Project-URL: Repository, https://github.com/regmibijay/yarp
Project-URL: Author Blog, https://blog.regmi.dev
Author-email: Bijay Regmi <bijay@regmi.dev>
License-File: LICENSE
Requires-Python: >=3.10
Requires-Dist: annoy>=1.17.3
Requires-Dist: levenshtein>=0.27.1
Requires-Dist: markupsafe==2.1.5
Requires-Dist: numpy<=1.26.4
Requires-Dist: pydantic>=2.11.9
Provides-Extra: cpu
Requires-Dist: sentence-transformers>=5.1.0; extra == 'cpu'
Requires-Dist: torch==2.8.0+cpu; (platform_machine != 'arm64' and platform_system != 'Darwin') and extra == 'cpu'
Requires-Dist: torch==2.8.0; (platform_machine == 'arm64' or platform_system == 'Darwin') and extra == 'cpu'
Provides-Extra: docs
Requires-Dist: sphinx-autobuild>=2024.4.16; extra == 'docs'
Requires-Dist: sphinx-rtd-theme>=2.0.0; extra == 'docs'
Requires-Dist: sphinx>=7.1.0; extra == 'docs'
Provides-Extra: gpu
Requires-Dist: sentence-transformers>=5.1.0; extra == 'gpu'
Requires-Dist: torch>=2.8.0; extra == 'gpu'
